{
  "name": "SetAttributes op",
  "description": "Set attributes on a block, or document-level metadata when block is empty.",
  "type": "hm://hyper.media/map",
  "required": [
    "type"
  ],
  "properties": {
    "type": {
      "type": "hm://hyper.media/string",
      "enum": [
        "SetAttributes"
      ]
    },
    "block": {
      "ref": "hm://hyper.media/string"
    },
    "attrs": {
      "type": "hm://hyper.media/list",
      "items": {
        "ref": "hm://seed.hyper.media/key-value"
      }
    }
  }
}
